setup.py
ngxPy.egg-info/PKG-INFO
ngxPy.egg-info/SOURCES.txt
ngxPy.egg-info/dependency_links.txt
ngxPy.egg-info/requires.txt
ngxPy.egg-info/top_level.txt
ngxpy/__init__.py
ngxpy/ngxpy.py