Metadata-Version: 1.1
Name: ngxPy
Version: 0.2.1
Summary: Python NGINX Plus Status Wrapper
Home-page: https://github.com/0snug0/ngxPy
Author: Eric
Author-email: elugo25111@gmail.com
License: UNKNOWN
Download-URL: https://github.com/0snug0/ngxPy/archive/master.zip
Platform: UNKNOWN
